LICENSE
MANIFEST.in
README.md
setup.py
bin/connman-dispatcher
connman_dispatcher/__init__.py
connman_dispatcher/detect.py
connman_dispatcher/utils.py
connman_dispatcher.egg-info/PKG-INFO
connman_dispatcher.egg-info/SOURCES.txt
connman_dispatcher.egg-info/dependency_links.txt
connman_dispatcher.egg-info/requires.txt
connman_dispatcher.egg-info/top_level.txt