Metadata-Version: 1.0
Name: connman-dispatcher
Version: 0.0.8
Summary: Call scripts on network changes
Home-page: http://github.com/a-sk/connman-dispatcher
Author: Alexandr Skurikhin
Author-email: a.skurikhin@gmail.com
License: Copyright (c) 2014 Alexandr Skurikhin
